[
    { "no": 1, "nama": "Andi", "alamat": "Jakarta","editor":"<span class=\"label label-danger\"><i class=\"icon icon-cross_mark\"></i>Edit</span>" },
    { "no": 2, "nama": "Budi", "alamat": "Bandung","editor":"<span class=\"label label-danger\"><i class=\"icon icon-cross_mark\"></i>Edit</span>" },
    { "no": 3, "nama": "Citra", "alamat": "Surabaya","editor":"<span class=\"label label-danger\"><i class=\"icon icon-cross_mark\"></i>Edit</span>" },
    { "no": 4, "nama": "Dedi", "alamat": "Medan","editor":"<span class=\"label label-danger\"><i class=\"icon icon-cross_mark\"></i>Edit</span>" },
    { "no": 5, "nama": "Eka", "alamat": "Yogyakarta","editor":"<span class=\"label label-danger\"><i class=\"icon icon-cross_mark\"></i>Edit</span>" },
    { "no": 6, "nama": "Fajar", "alamat": "Semarang","editor":"<span class=\"label label-danger\"><i class=\"icon icon-cross_mark\"></i>Edit</span>" },
    { "no": 7, "nama": "Gina", "alamat": "Makassar","editor":"<span class=\"label label-danger\"><i class=\"icon icon-cross_mark\"></i>Edit</span>" },
    { "no": 8, "nama": "Hadi", "alamat": "Balikpapan","editor":"<span class=\"label label-danger\"><i class=\"icon icon-cross_mark\"></i>Edit</span>" },
    { "no": 9, "nama": "Ika", "alamat": "Denpasar","editor":"<span class=\"label label-danger\"><i class=\"icon icon-cross_mark\"></i>Edit</span>" },
    { "no": 10, "nama": "Joko", "alamat": "Palembang","editor":"<span class=\"label label-danger\"><i class=\"icon icon-cross_mark\"></i>Edit</span>" },
    { "no": 11, "nama": "Kiki", "alamat": "Pontianak","editor":"<span class=\"label label-danger\"><i class=\"icon icon-cross_mark\"></i>Edit</span>" },
    { "no": 12, "nama": "Lina", "alamat": "Manado","editor":"<span class=\"label label-danger\"><i class=\"icon icon-cross_mark\"></i>Edit</span>" }
]